C2H5OH/__init__.py
C2H5OH/attack.py
C2H5OH/core.py
C2H5OH/utils.py
C2H5OH/version.py
Tests/__init__.py
Tests/test.py
c2h5oh-0.1.3.dist-info/licenses/LICENSE.txt
c2h5oh-0.1.3.dist-info/METADATA
c2h5oh-0.1.3.dist-info/WHEEL
c2h5oh-0.1.3.dist-info/top_level.txt
c2h5oh-0.1.3.dist-info/RECORD
