Metadata-Version: 2.4
Name: C2H5OH
Version: 0.1.3
Summary: Thuật toán mã hóa cổ điển và đặc biệt: Tăng-Giảm-Tuần-Hoàn, Hố Đen, mô phỏng BB84.
Home-page: https://github.com/teone-sensei/C2H5OH
Author: テオネ先生
Author-email: theonlyone11k2@gmail.com
License: GPLv3
Classifier: Programming Language :: Python :: 3
Classifier: License :: OSI Approved :: GNU General Public License v3 (GPLv3)
Classifier: Operating System :: OS Independent
Classifier: Topic :: Security :: Cryptography
Requires-Python: >=3.6
License-File: LICENSE.txt
Dynamic: author
Dynamic: author-email
Dynamic: classifier
Dynamic: home-page
Dynamic: license
Dynamic: license-file
Dynamic: requires-python
Dynamic: summary
